equasolver/__init__.py
equasolver/__main__.py
equasolver/components.py
equasolver/linear.py
equasolver/quadratic.py
equasolver-0.0.2.dist-info/LICENSE
equasolver-0.0.2.dist-info/METADATA
equasolver-0.0.2.dist-info/WHEEL
equasolver-0.0.2.dist-info/top_level.txt
equasolver-0.0.2.dist-info/RECORD
