Metadata-Version: 2.1
Name: equasolver
Version: 0.0.2
Summary: A simple package to solve linear and quadratic equations
Home-page: https://github.com/snehashish090/equasolver
Author: Snehashish Laskar
Author-email: snehashish.laskar@gmail.com
License: MIT License
License-File: LICENSE
